<?xml version="1.0" encoding="utf-8" ?>

<Schema>
  <Entity Name="WorkActivity" Tags="StaticData" OrderBy="SortOrder" Interface="IStaticData">
    <Key Name="Id" Type="guid" />
    <Property Name="Name" Type="string[128]" />
    <Property Name="SortOrder" Type="Int32" />
    <Property Name="Default" Type="boolean" />
    <Property Name="Hidden" Type="boolean" />
    <Property Name="FreeText" Type="boolean" />
    <Index Unique="true">
      <Member Name="Name" />
    </Index>
    <Data>
      <Row Id="2ec85064-aaf1-41ef-8159-01bee8fae82a" Name="NIHR RSS resource article development (written/recorded/animated)" />
      <Row Id="1cff481e-96ae-4888-8a7e-740f317e39fa" Name="Course or workshop development" />
      <Row Id="82cf2ba5-1395-4f75-9d41-c20f55f4179d" Name="Course or workship delivery" />
      <Row Id="fe4f8faf-ff96-4271-9f48-0af17d936a75" Name="RSS Training/Mentoring/Supervision session etc" />
      <Row Id="1ac14113-5994-4c32-9914-dafb1c23cb22" Name="RSS publication" />
      <Row Id="d5398de9-3ac3-473b-8596-e5b593ca7a68" Name="NIHR RSS methods academy research activity" />
      <Row Id="e85c7de3-7827-437c-a36c-a2d22ae2a05e" Name="NIHR RSS methods academy research time" />
      <Row Id="79699038-412d-475a-9ed7-e51838863115" Name="Other" FreeText="true" />
    </Data>
  </Entity>
</Schema>
